LICENSE
setup.py
lexconvert/__init__.py
lexconvert/__main__.py
lexconvert.egg-info/PKG-INFO
lexconvert.egg-info/SOURCES.txt
lexconvert.egg-info/dependency_links.txt
lexconvert.egg-info/entry_points.txt
lexconvert.egg-info/top_level.txt