Metadata-Version: 2.1
Name: lexconvert
Version: 0.43
Summary: Convert phoneme codes and lexicon formats for English speech synths
Home-page: http://ssb22.user.srcf.net/lexconvert/
Author: Silas S. Brown
Author-email: ssb22@cam.ac.uk
License: Apache 2
Platform: any
Classifier: Programming Language :: Python :: 2
Classifier: Programming Language :: Python :: 3
Classifier: License :: OSI Approved :: Apache Software License
Classifier: Operating System :: OS Independent
Requires-Python: >=2.3,!=3.0.*,!=3.1.*,!=3.2.*,!=3.3.*,!=3.4.*
License-File: LICENSE
